MANIFEST.in
NEWS.txt
README.rst
setup.py
src/memoized.py
src/memoized.egg-info/PKG-INFO
src/memoized.egg-info/SOURCES.txt
src/memoized.egg-info/dependency_links.txt
src/memoized.egg-info/not-zip-safe
src/memoized.egg-info/requires.txt
src/memoized.egg-info/top_level.txt