Metadata-Version: 1.1
Name: memoized
Version: 0.1
Summary: General purpose efficient memoization
Home-page: https://bitbucket.org/gsakkis/memoized
Author: George Sakkis
Author-email: george.sakkis@gmail.com
License: MIT
Platform: UNKNOWN
Classifier: Development Status :: 4 - Beta
Classifier: Intended Audience :: Developers
Classifier: Operating System :: OS Independent
Classifier: Programming Language :: Python :: 2.7
Classifier: Topic :: Software Development :: Libraries :: Python Modules
Classifier: License :: OSI Approved :: MIT License
